ui/ui.py
w3mo_kivy-0.1.1.dist-info/LICENSE
w3mo_kivy-0.1.1.dist-info/METADATA
w3mo_kivy-0.1.1.dist-info/WHEEL
w3mo_kivy-0.1.1.dist-info/top_level.txt
w3mo_kivy-0.1.1.dist-info/RECORD
