Metadata-Version: 2.1
Name: w3mo-kivy
Version: 0.1.1
Summary: wemo control library
Home-page: https://github.com/mghelton/w3mo
Author: Gage Helton
Author-email: gagehelton@gmail.com
License: UNKNOWN
Platform: UNKNOWN
Classifier: Programming Language :: Python :: 3
Classifier: License :: OSI Approved :: MIT License
Classifier: Operating System :: OS Independent
Requires-Dist: altgraph (==0.17)
Requires-Dist: certifi (==2020.4.5.2)
Requires-Dist: chardet (==3.0.4)
Requires-Dist: docutils (==0.16)
Requires-Dist: idna (==2.9)
Requires-Dist: Kivy (==1.11.1)
Requires-Dist: Kivy-Garden (==0.1.4)
Requires-Dist: kivymd
Requires-Dist: macholib (==1.14)
Requires-Dist: Pillow (==7.1.2)
Requires-Dist: Pygments (==2.6.1)
Requires-Dist: PyInstaller (==3.6)
Requires-Dist: requests (==2.23.0)
Requires-Dist: urllib3 (==1.25.9)
Requires-Dist: w3mo (>=0.1.7)
